pyldaplite/__init__.py
pyldaplite-0.2.0.dist-info/METADATA
pyldaplite-0.2.0.dist-info/WHEEL
pyldaplite-0.2.0.dist-info/top_level.txt
pyldaplite-0.2.0.dist-info/RECORD
