Metadata-Version: 2.1
Name: pyldaplite
Version: 0.2.0
Summary: Simple package for LDAP
Home-page: https://github.com/lixxu/pyldaplite
Author: Lix Xu
Author-email: xuzenglin@gmail.com
License: BSD
Platform: any
Classifier: Environment :: Web Environment
Classifier: Intended Audience :: Developers
Classifier: License :: OSI Approved :: BSD License
Classifier: Operating System :: OS Independent
Classifier: Programming Language :: Python
Classifier: Topic :: Internet :: WWW/HTTP :: Dynamic Content
Classifier: Topic :: Software Development :: Libraries :: Python Modules
Requires-Dist: python-ldap
